midi_utils/__init__.py
midi_utils/adsr.py
midi_utils/arp.py
midi_utils/chord.py
midi_utils/constants.py
midi_utils/scale.py
midi_utils/utils.py
midi_utils-1.3.3.dist-info/METADATA
midi_utils-1.3.3.dist-info/WHEEL
midi_utils-1.3.3.dist-info/licenses/LICENSE
midi_utils-1.3.3.dist-info/RECORD
