Metadata-Version: 2.4
Name: midi-utils
Version: 1.3.3
Summary: Lightweight, pure-python utility for generating scales of midi notes. Includes support for microtunings via asclpy
Project-URL: Homepage, https://gitlab.com/gltd/midi-utils
Project-URL: Repository, https://gitlab.com/gltd/midi-utils
Project-URL: Issues, https://gitlab.com/gltd/midi-utils/-/issues
Author-email: Brian Abelson <brian@abelson.live>
License: MIT
License-File: LICENSE
Keywords: arpeggio,audio,chord,midi,music,scale
Classifier: Development Status :: 4 - Beta
Classifier: Intended Audience :: Developers
Classifier: License :: OSI Approved :: MIT License
Classifier: Programming Language :: Python :: 3
Classifier: Programming Language :: Python :: 3.13
Classifier: Topic :: Multimedia :: Sound/Audio :: MIDI
Requires-Python: >=3.13
Requires-Dist: asclpy>=0.1.0
